{
  "depth":4,
  "scene":
  [
    {
      "type":"SPHERE",
      "color": {
        "red": 255,
        "green": 255,
        "blue": 255
      },
      "pos":{
        "x":0,
        "y":0.4,
        "z":4
      },
      "reflection_index": 0.0,
      "refraction": 0.0,
      "refraction_index": 1.33,
      "diffuse": 0.0,
      "radius": 0.50
    },
    {
      "comment":"sol",
      "type": "PLANE",
      "color": {
        "red":200,
        "green":255,
        "blue":40
      },
      "pos": {
        "x":0,
        "y":-6,
        "z":2
      },
      "reflection_index": 0.0,
      "refraction": 1.0,
      "refraction_index": 0.0,
      "diffuse": 0.0,
      "normal": {
        "x":0,
        "y":0.1,
        "z":0
      }
    },
    {
      "comment":"Mur Gauche",
      "type":"PLANE",
      "color":{
        "red":206,
        "green":206,
        "blue":206
      },
      "pos":{
        "x":-20,
        "y":0,
        "z":0
      },
      "reflection_index": 0.0,
      "refraction": 0.0,
      "refraction_index": 0.0,
      "diffuse": 0.1,
      "normal":{
        "x":0.4,
        "y":0,
        "z":0
      }
    },
    {
      "comment":"Mur droite",
      "type":"PLANE",
      "color":{
        "red":200,
        "green":55,
        "blue":100
      },
      "pos":{
        "x":20,
        "y":0,
        "z":0
      },
      "reflection_index": 0.0,
      "refraction": 0.0,
      "refraction_index": 0.0,
      "diffuse": 0.8,
      "normal":{
        "x":-0.4,
        "y":0,
        "z":0
      }
    }
  ],
  "lights": [
    {
      "type": "SPOTLIGHT",
      "color": {
        "red": 255,
        "green": 255,
        "blue": 255
      },
      "pos": {
        "x": 0,
        "y": 0,
        "z": 100
      },
      "reflection_index": 0.0,
      "refraction": 0.0,
      "refraction_index": 0.0,
      "diffuse": 0.0,
      "dir": {
        "x": 0,
        "y": 0,
        "z": 0
      },
      "intensity": 0.7
    }
  ]
}
